printy/__init__.py
printy/__main__.py
printy/core.py
printy/exceptions.py
printy/flags.py
printy/helpme.py
printy-3.0.1.dist-info/licenses/LICENSE
printy-3.0.1.dist-info/METADATA
printy-3.0.1.dist-info/WHEEL
printy-3.0.1.dist-info/top_level.txt
printy-3.0.1.dist-info/RECORD
