Metadata-Version: 2.4
Name: printy
Version: 3.0.1
Summary: Colorize the print statement by global or inline flags
Author-email: Edgardo Obregon <edraobdu@gmail.com>
License: MIT
Project-URL: Homepage, https://github.com/edraobdu/printy
Project-URL: Repository, https://github.com/edraobdu/printy
Project-URL: Issues, https://github.com/edraobdu/printy/issues
Classifier: Development Status :: 5 - Production/Stable
Classifier: Intended Audience :: Developers
Classifier: License :: OSI Approved :: MIT License
Classifier: Operating System :: OS Independent
Classifier: Programming Language :: Python
Classifier: Programming Language :: Python :: 3
Classifier: Programming Language :: Python :: 3.10
Classifier: Programming Language :: Python :: 3.11
Classifier: Programming Language :: Python :: 3.12
Classifier: Programming Language :: Python :: 3.13
Classifier: Programming Language :: Python :: 3.14
Requires-Python: >=3.10
License-File: LICENSE
Provides-Extra: dev
Requires-Dist: coverage[toml]>=7.0.0; extra == "dev"
Requires-Dist: ruff>=0.1.0; extra == "dev"
Requires-Dist: pre-commit>=3.0.0; extra == "dev"
Requires-Dist: mypy>=1.0.0; extra == "dev"
Dynamic: license-file
